shortlink/__init__.py
shortlink/__main__.py
PyLeb_ShortLink-1.0.0.dist-info/LICENSE
PyLeb_ShortLink-1.0.0.dist-info/METADATA
PyLeb_ShortLink-1.0.0.dist-info/WHEEL
PyLeb_ShortLink-1.0.0.dist-info/entry_points.txt
PyLeb_ShortLink-1.0.0.dist-info/top_level.txt
PyLeb_ShortLink-1.0.0.dist-info/RECORD
