Metadata-Version: 2.1
Name: PyLeb-ShortLink
Version: 1.0.0
Summary: a library to short links using tinyurl
Author-email: mesteranas <anasformohammed@gmail.com>
License: GNU GENERAL PUBLIC LICENSE
Project-URL: Homepage, https://github.com/mesteranas/PyLeb_ShortLink
Keywords: links,short links,link shortner
Classifier: Programming Language :: Python
Classifier: Programming Language :: Python :: 3
Requires-Python: >=3.9
License-File: LICENSE
Requires-Dist: requests
